setup.py
qing/__init__.py
qing.egg-info/PKG-INFO
qing.egg-info/SOURCES.txt
qing.egg-info/dependency_links.txt
qing.egg-info/top_level.txt
qing.egg-info/zip-safe