Metadata-Version: 1.1
Name: qing
Version: 0.1.1
Summary: Lightweight ops tool
Home-page: https://github.com/qingup/qing
Author: Qing Dev
Author-email: qingup.io@gmail.com
License: UNKNOWN
Platform: Independent
Classifier: Development Status :: 4 - Beta
Classifier: Intended Audience :: Developers
Classifier: Programming Language :: Python
Classifier: Programming Language :: Python :: 2.7
Classifier: Programming Language :: Python :: Implementation :: CPython
Classifier: Operating System :: OS Independent
Classifier: Topic :: Utilities
